refreshAaveApiToken/__init__.py
refreshAaveApiToken/__main__.py
refresh_aave_api_token-1.0.0.dist-info/METADATA
refresh_aave_api_token-1.0.0.dist-info/WHEEL
refresh_aave_api_token-1.0.0.dist-info/entry_points.txt
refresh_aave_api_token-1.0.0.dist-info/top_level.txt
refresh_aave_api_token-1.0.0.dist-info/RECORD
