Metadata-Version: 2.1
Name: refresh-aave-api-token
Version: 1.0.0
Summary: A package to refresh access tokens for CryptoTalk Aave Rest APIs.
Home-page: UNKNOWN
Author: Avyact Jain
Author-email: avyactjain@gmail.com
License: UNKNOWN
Project-URL: SignUp, https://aaveonmobile-home.auth.us-east-2.amazoncognito.com/signup?client_id=5b6893vo53h5jo7jk8prhphei4&response_type=code&scope=/aave/address%20/aave/allowance%20/aave/borrow%20/aave/configuration%20/aave/deposit%20/aave/rates%20/aave/repay%20/aave/setUserUseReserveAsCollateral%20/aave/swapBorrowRateMode%20/aave/user-health%20/aave/withdraw%20aws.cognito.signin.user.admin%20email%20openid%20phone%20profile&redirect_uri=https://access-token-fiz3rywh2a-an.a.run.app/token
Project-URL: Twitter, https://twitter.com/CryptoTalk_
Platform: UNKNOWN
Requires-Dist: boto3
Requires-Dist: argparse
